{
  "generated_at": "2025-11-21T00:18:31.369870+08:00",
  "total_titles_processed": 315,
  "failed_sources": [],
  "trends": [
    {
      "keyword_group": "美股",
      "match_count": 4,
      "titles": [
        {
          "title": "科技股力撑美股反弹，英伟达绩后一度大涨6%，美元涨回100，加密货币盘中大跌",
          "url": "https://wallstreetcn.com/articles/3759700",
          "source": "华尔街见闻",
          "ranks": [
            2
          ],
          "is_new": false,
          "appearance_count": 1,
          "time_info": "00时18分"
        },
        {
          "title": "科兴生物被美股“劝退”",
          "url": "https://www.toutiao.com/trending/7574778331892026934/",
          "source": "今日头条",
          "ranks": [
            15
          ],
          "is_new": false,
          "appearance_count": 1,
          "time_info": "00时18分"
        },
        {
          "title": "美光科技回吐美股盘初超过1%的涨幅，并转而下跌3.6%。 瑞银将美光科技的股价目标从245美元上调至275美元，同时维持买入评级，理由是内存供应紧张状况将延续至2026年底。",
          "url": "https://wallstreetcn.com/livenews/3008042",
          "source": "华尔街见闻-快讯",
          "ranks": [
            23
          ],
          "is_new": false,
          "appearance_count": 1,
          "time_info": "00时18分"
        },
        {
          "title": "AMD美股盘初一度涨约4%，沙特AI公司Humain宣布将与AMD、思科系统公司成立合资企业，计划于2030年前在沙特阿拉伯建设并运营高达1吉瓦（GW）的AI基础设施。",
          "url": "https://wallstreetcn.com/livenews/3008041",
          "source": "华尔街见闻-快讯",
          "ranks": [
            24
          ],
          "is_new": false,
          "appearance_count": 1,
          "time_info": "00时18分"
        }
      ]
    },
    {
      "keyword_group": "多氟多 002407",
      "match_count": 1,
      "titles": [
        {
          "title": "【数据看盘】四家实力游资激烈博弈五连板人气股 多路资金大笔抛售多氟多",
          "url": "https://www.cls.cn/detail/2206416",
          "source": "财联社热门",
          "ranks": [
            8
          ],
          "is_new": false,
          "appearance_count": 1,
          "time_info": "00时18分"
        }
      ]
    },
    {
      "keyword_group": "美债",
      "match_count": 1,
      "titles": [
        {
          "title": "英伟达业绩驱散悲观情绪，“悲喜交织”就业数据后，美股指数高开高走，美债上扬",
          "url": "https://wallstreetcn.com/articles/3759753",
          "source": "华尔街见闻",
          "ranks": [
            5
          ],
          "is_new": false,
          "appearance_count": 1,
          "time_info": "00时18分"
        }
      ]
    }
  ],
  "report_image_url": "https://hugoszhaha.github.io/TrendRadar/img/news.jpg"
}